aioredis_rpc/__init__.py
aioredis_rpc/msgpack_ext.py
aioredis_rpc-1.1.0.dist-info/LICENSE.txt
aioredis_rpc-1.1.0.dist-info/METADATA
aioredis_rpc-1.1.0.dist-info/WHEEL
aioredis_rpc-1.1.0.dist-info/top_level.txt
aioredis_rpc-1.1.0.dist-info/zip-safe
aioredis_rpc-1.1.0.dist-info/RECORD
