Metadata-Version: 2.1
Name: aioredis-rpc
Version: 1.1.0
Summary: An RPC library based on aioredis, msgpack, and pydantic.
Home-page: http://github.com/matutter/aioredis-rpc
Author: Mathew Utter
Author-email: mcutter.svc@gmail.com
License: MIT
Keywords: aioredis msgpack python redis rpc
Platform: UNKNOWN
Classifier: Programming Language :: Python :: 3.7
Classifier: Intended Audience :: Developers
Classifier: License :: OSI Approved :: MIT License
Classifier: Natural Language :: English
Classifier: Operating System :: POSIX :: Linux
Classifier: Operating System :: MacOS :: MacOS X
Classifier: Operating System :: POSIX :: BSD
Classifier: Operating System :: Microsoft :: Windows :: Windows Vista
Classifier: Operating System :: Microsoft :: Windows :: Windows 7
Classifier: Operating System :: Microsoft :: Windows :: Windows 8
Classifier: Operating System :: Microsoft :: Windows :: Windows 8.1
Classifier: Operating System :: Microsoft :: Windows :: Windows 10
Classifier: Operating System :: OS Independent
Classifier: Programming Language :: Python
Classifier: Programming Language :: Python :: 3
Classifier: Programming Language :: Python :: 3 :: Only
Classifier: Programming Language :: Python :: 3.8
Classifier: Programming Language :: Python :: 3.9
Classifier: Programming Language :: Python :: 3.10
Classifier: Topic :: Software Development :: Build Tools
Classifier: Topic :: Software Development :: Libraries
Classifier: Topic :: System :: Filesystems
Classifier: Topic :: System :: Monitoring
Classifier: Topic :: Utilities
Requires: pydantic
Requires: msgpack
Requires: aioredis
Requires: hiredis
Requires-Python: >=3.6.1
License-File: LICENSE.txt
Requires-Dist: pydantic (==1.8.2)
Requires-Dist: msgpack (==1.0.2)
Requires-Dist: aioredis (==2.0.0a1)
Requires-Dist: hiredis (==2.0.0)
